halo_splunk/__init__.py
halo_splunk/hspi.py
halo_splunk_d-1.0.0.dist-info/LICENSE.txt
halo_splunk_d-1.0.0.dist-info/METADATA
halo_splunk_d-1.0.0.dist-info/WHEEL
halo_splunk_d-1.0.0.dist-info/entry_points.txt
halo_splunk_d-1.0.0.dist-info/top_level.txt
halo_splunk_d-1.0.0.dist-info/RECORD
